pygreet.py
pygreet-1.0.1.dist-info/LICENSE
pygreet-1.0.1.dist-info/METADATA
pygreet-1.0.1.dist-info/WHEEL
pygreet-1.0.1.dist-info/top_level.txt
pygreet-1.0.1.dist-info/RECORD
