Metadata-Version: 2.1
Name: pygreet
Version: 1.0.1
Summary: A simple greeting python package.
Home-page: https://github.com/LordDashMe/pygreet
Author: Joshua Clifford Reyes
Author-email: reyesjoshuaclifford@gmail.com
Classifier: Programming Language :: Python :: 3
Classifier: Programming Language :: Python :: 3.6
Classifier: Programming Language :: Python :: 3.10
Classifier: License :: OSI Approved :: MIT License
Classifier: Operating System :: OS Independent
License-File: LICENSE
Requires-Dist: blessings
Provides-Extra: dev
Requires-Dist: pytest ; extra == 'dev'
